{
  "$schema": "https://developer.microsoft.com/json-schemas/fabric/item/report/definition/visualContainer/2.8.0/schema.json",
  "name": "e0eb9b28bd5a727f575f",
  "position": {
    "x": 1107.9726651480637,
    "y": 1272.4373576309795,
    "z": 7000,
    "height": 597.26651480637815,
    "width": 796.3553530751708,
    "tabOrder": 7000
  },
  "visual": {
    "visualType": "barChart",
    "query": {
      "queryState": {
        "Category": {
          "projections": [
            {
              "field": {
                "Column": {
                  "Expression": {
                    "SourceRef": {
                      "Entity": "Dim_ServiceLine"
                    }
                  },
                  "Property": "ServiceLine"
                }
              },
              "queryRef": "Dim_ServiceLine.ServiceLine",
              "nativeQueryRef": "ServiceLine",
              "active": true
            }
          ]
        },
        "Y": {
          "projections": [
            {
              "field": {
                "Measure": {
                  "Expression": {
                    "SourceRef": {
                      "Entity": "Fact_Encounters"
                    }
                  },
                  "Property": "_% Operating Margin"
                }
              },
              "queryRef": "Fact_Encounters._% Operating Margin",
              "nativeQueryRef": "_% Operating Margin",
              "format": "0.0%;-0.0%;0.0%"
            }
          ]
        }
      },
      "sortDefinition": {
        "sort": [
          {
            "field": {
              "Measure": {
                "Expression": {
                  "SourceRef": {
                    "Entity": "Fact_Encounters"
                  }
                },
                "Property": "_% Operating Margin"
              }
            },
            "direction": "Descending"
          }
        ],
        "isDefaultSort": true
      }
    },
    "objects": {
      "dataPoint": [
        {
          "properties": {
            "fill": {
              "solid": {
                "color": {
                  "expr": {
                    "Conditional": {
                      "Cases": [
                        {
                          "Condition": {
                            "And": {
                              "Left": {
                                "Comparison": {
                                  "ComparisonKind": 2,
                                  "Left": {
                                    "Measure": {
                                      "Expression": {
                                        "SourceRef": {
                                          "Entity": "Fact_Encounters"
                                        }
                                      },
                                      "Property": "_% Operating Margin"
                                    }
                                  },
                                  "Right": {
                                    "RangePercent": {
                                      "Min": {
                                        "ScopedEval": {
                                          "Expression": {
                                            "Aggregation": {
                                              "Expression": {
                                                "ScopedEval": {
                                                  "Expression": {
                                                    "Measure": {
                                                      "Expression": {
                                                        "SourceRef": {
                                                          "Entity": "Fact_Encounters"
                                                        }
                                                      },
                                                      "Property": "_% Operating Margin"
                                                    }
                                                  },
                                                  "Scope": [
                                                    {
                                                      "AllRolesRef": {}
                                                    }
                                                  ]
                                                }
                                              },
                                              "Function": 3
                                            }
                                          },
                                          "Scope": []
                                        }
                                      },
                                      "Max": {
                                        "ScopedEval": {
                                          "Expression": {
                                            "Aggregation": {
                                              "Expression": {
                                                "ScopedEval": {
                                                  "Expression": {
                                                    "Measure": {
                                                      "Expression": {
                                                        "SourceRef": {
                                                          "Entity": "Fact_Encounters"
                                                        }
                                                      },
                                                      "Property": "_% Operating Margin"
                                                    }
                                                  },
                                                  "Scope": [
                                                    {
                                                      "AllRolesRef": {}
                                                    }
                                                  ]
                                                }
                                              },
                                              "Function": 4
                                            }
                                          },
                                          "Scope": []
                                        }
                                      },
                                      "Percent": 0.002
                                    }
                                  }
                                }
                              },
                              "Right": {
                                "Comparison": {
                                  "ComparisonKind": 3,
                                  "Left": {
                                    "Measure": {
                                      "Expression": {
                                        "SourceRef": {
                                          "Entity": "Fact_Encounters"
                                        }
                                      },
                                      "Property": "_% Operating Margin"
                                    }
                                  },
                                  "Right": {
                                    "Literal": {
                                      "Value": "0.22D"
                                    }
                                  }
                                }
                              }
                            }
                          },
                          "Value": {
                            "Literal": {
                              "Value": "'#07782B'"
                            }
                          }
                        },
                        {
                          "Condition": {
                            "Comparison": {
                              "ComparisonKind": 3,
                              "Left": {
                                "Measure": {
                                  "Expression": {
                                    "SourceRef": {
                                      "Entity": "Fact_Encounters"
                                    }
                                  },
                                  "Property": "_% Operating Margin"
                                }
                              },
                              "Right": {
                                "Literal": {
                                  "Value": "0.2D"
                                }
                              }
                            }
                          },
                          "Value": {
                            "Literal": {
                              "Value": "'#B90B0B'"
                            }
                          }
                        },
                        {
                          "Condition": {
                            "Comparison": {
                              "ComparisonKind": 3,
                              "Left": {
                                "Measure": {
                                  "Expression": {
                                    "SourceRef": {
                                      "Entity": "Fact_Encounters"
                                    }
                                  },
                                  "Property": "_% Operating Margin"
                                }
                              },
                              "Right": {
                                "Literal": {
                                  "Value": "0.22D"
                                }
                              }
                            }
                          },
                          "Value": {
                            "Literal": {
                              "Value": "'#808080'"
                            }
                          }
                        }
                      ]
                    }
                  }
                }
              }
            }
          },
          "selector": {
            "data": [
              {
                "dataViewWildcard": {
                  "matchingOption": 1
                }
              }
            ]
          }
        }
      ],
      "labels": [
        {
          "properties": {
            "show": {
              "expr": {
                "Literal": {
                  "Value": "true"
                }
              }
            },
            "color": {
              "solid": {
                "color": {
                  "expr": {
                    "ThemeDataColor": {
                      "ColorId": 5,
                      "Percent": 0
                    }
                  }
                }
              }
            },
            "enableBackground": {
              "expr": {
                "Literal": {
                  "Value": "true"
                }
              }
            },
            "backgroundColor": {
              "solid": {
                "color": {
                  "expr": {
                    "Literal": {
                      "Value": "'#b3b3b3'"
                    }
                  }
                }
              }
            },
            "enableDetailDataLabel": {
              "expr": {
                "Literal": {
                  "Value": "true"
                }
              }
            },
            "detailColor": {
              "solid": {
                "color": {
                  "expr": {
                    "ThemeDataColor": {
                      "ColorId": 5,
                      "Percent": 0
                    }
                  }
                }
              }
            },
            "detailFontSize": {
              "expr": {
                "Literal": {
                  "Value": "21D"
                }
              }
            }
          }
        }
      ],
      "categoryAxis": [
        {
          "properties": {
            "labelColor": {
              "solid": {
                "color": {
                  "expr": {
                    "ThemeDataColor": {
                      "ColorId": 5,
                      "Percent": 0
                    }
                  }
                }
              }
            },
            "bold": {
              "expr": {
                "Literal": {
                  "Value": "true"
                }
              }
            },
            "fontSize": {
              "expr": {
                "Literal": {
                  "Value": "15D"
                }
              }
            }
          }
        }
      ],
      "valueAxis": [
        {
          "properties": {
            "labelColor": {
              "solid": {
                "color": {
                  "expr": {
                    "ThemeDataColor": {
                      "ColorId": 5,
                      "Percent": 0
                    }
                  }
                }
              }
            },
            "bold": {
              "expr": {
                "Literal": {
                  "Value": "true"
                }
              }
            },
            "fontSize": {
              "expr": {
                "Literal": {
                  "Value": "15D"
                }
              }
            },
            "gridlineColor": {
              "solid": {
                "color": {
                  "expr": {
                    "Literal": {
                      "Value": "'#E61929'"
                    }
                  }
                }
              }
            },
            "gridlineShow": {
              "expr": {
                "Literal": {
                  "Value": "false"
                }
              }
            }
          }
        }
      ]
    },
    "visualContainerObjects": {
      "border": [
        {
          "properties": {
            "show": {
              "expr": {
                "Literal": {
                  "Value": "true"
                }
              }
            },
            "color": {
              "solid": {
                "color": {
                  "expr": {
                    "Literal": {
                      "Value": "'#E61929'"
                    }
                  }
                }
              }
            }
          }
        }
      ],
      "background": [
        {
          "properties": {
            "color": {
              "solid": {
                "color": {
                  "expr": {
                    "Literal": {
                      "Value": "'#b3b3b3'"
                    }
                  }
                }
              }
            }
          }
        }
      ],
      "title": [
        {
          "properties": {
            "text": {
              "expr": {
                "Literal": {
                  "Value": "'Margin % by Service Line'"
                }
              }
            },
            "fontColor": {
              "solid": {
                "color": {
                  "expr": {
                    "ThemeDataColor": {
                      "ColorId": 5,
                      "Percent": 0
                    }
                  }
                }
              }
            },
            "alignment": {
              "expr": {
                "Literal": {
                  "Value": "'center'"
                }
              }
            },
            "background": {
              "solid": {
                "color": {
                  "expr": {
                    "Literal": {
                      "Value": "'#b3b3b3'"
                    }
                  }
                }
              }
            },
            "fontSize": {
              "expr": {
                "Literal": {
                  "Value": "29D"
                }
              }
            },
            "bold": {
              "expr": {
                "Literal": {
                  "Value": "true"
                }
              }
            }
          }
        }
      ]
    },
    "drillFilterOtherVisuals": true
  }
}